aia_chaser/__init__.py
aia_chaser/chaser.py
aia_chaser/constants.py
aia_chaser/exceptions.py
aia_chaser/utils/__init__.py
aia_chaser/utils/cert_utils.py
aia_chaser/utils/type_utils.py
aia_chaser/utils/url.py
aia_chaser/verify.py
aia_chaser-3.3.0.dist-info/LICENSE
aia_chaser-3.3.0.dist-info/METADATA
aia_chaser-3.3.0.dist-info/WHEEL
aia_chaser-3.3.0.dist-info/RECORD
