Metadata-Version: 2.3
Name: aia-chaser
Version: 3.3.0
Summary: Chase authority information access from a host certificate to complete the chain of trust.
License: MIT
Keywords: AIA,SSL,TLS,X.509,Certificate Chain
Author: Josep Pon Farreny
Author-email: jponfarreny@gmail.com
Requires-Python: >=3.8,<4.0
Classifier: Development Status :: 5 - Production/Stable
Classifier: Intended Audience :: Developers
Classifier: License :: OSI Approved :: MIT License
Classifier: Programming Language :: Python
Classifier: Programming Language :: Python :: 3.8
Classifier: Programming Language :: Python :: 3.9
Classifier: Programming Language :: Python :: 3.10
Classifier: Programming Language :: Python :: 3.11
Classifier: Programming Language :: Python :: 3.12
Classifier: Programming Language :: Python :: 3.13
Classifier: Programming Language :: Python :: 3.14
Classifier: Programming Language :: Python :: Implementation :: CPython
Classifier: Programming Language :: Python :: Implementation :: PyPy
Classifier: Topic :: Internet :: WWW/HTTP
Classifier: Topic :: Security
Classifier: Topic :: System :: Networking
Requires-Dist: cryptography (>=40.0)
Project-URL: Documentation, https://aia-chaser.readthedocs.io/
Project-URL: Repository, https://github.com/jponf/aia-chaser
Project-URL: changelog, https://aia-chaser.readthedocs.io/en/stable/changelog/
